LICENSE.txt
README.md
setup.cfg
setup.py
sbol3/__init__.py
sbol3/attachment.py
sbol3/boolean_property.py
sbol3/collection.py
sbol3/combderiv.py
sbol3/component.py
sbol3/compref.py
sbol3/config.py
sbol3/constants.py
sbol3/constraint.py
sbol3/custom.py
sbol3/datetime_property.py
sbol3/document.py
sbol3/error.py
sbol3/expdata.py
sbol3/extdef.py
sbol3/feature.py
sbol3/float_property.py
sbol3/identified.py
sbol3/implementation.py
sbol3/int_property.py
sbol3/interaction.py
sbol3/interface.py
sbol3/localsub.py
sbol3/location.py
sbol3/model.py
sbol3/object.py
sbol3/om_compound.py
sbol3/om_prefix.py
sbol3/om_unit.py
sbol3/ownedobject.py
sbol3/participation.py
sbol3/property_base.py
sbol3/provenance.py
sbol3/refobj_property.py
sbol3/seqfeat.py
sbol3/sequence.py
sbol3/subcomponent.py
sbol3/text_property.py
sbol3/toplevel.py
sbol3/typing.py
sbol3/uri_property.py
sbol3/util.py
sbol3/utils.py
sbol3/validation.py
sbol3/varcomp.py
sbol3/rdf/sbol3-shapes.ttl
sbol3_for_pudu.egg-info/PKG-INFO
sbol3_for_pudu.egg-info/SOURCES.txt
sbol3_for_pudu.egg-info/dependency_links.txt
sbol3_for_pudu.egg-info/requires.txt
sbol3_for_pudu.egg-info/top_level.txt
test/test_annotation.py
test/test_attachment.py
test/test_collection.py
test/test_combderiv.py
test/test_component.py
test/test_compref.py
test/test_config.py
test/test_custom.py
test/test_document.py
test/test_examples.py
test/test_expdata.py
test/test_extdef.py
test/test_extension.py
test/test_feature.py
test/test_identified.py
test/test_implementation.py
test/test_interaction.py
test/test_interface.py
test/test_localsub.py
test/test_location.py
test/test_module.py
test/test_object.py
test/test_om_compound.py
test/test_om_prefix.py
test/test_om_unit.py
test/test_ownedobject.py
test/test_participation.py
test/test_property.py
test/test_provenance.py
test/test_referenced_object.py
test/test_roundtrip.py
test/test_seqfeat.py
test/test_sequence.py
test/test_style.py
test/test_subcomponent.py
test/test_text_property.py
test/test_toplevel.py
test/test_util.py
test/test_utils.py
test/test_validation.py
test/test_varcomp.py