Metadata-Version: 2.1
Name: sbol3-for-pudu
Version: 1.0.0a1
Summary: Python implementation of SBOL 3 standard compatible with PUDU
Home-page: https://github.com/Gonza10V/pySBOL3
Author: Gonzalo Vidal
Author-email: gvidal1011@gmail.com
License: MIT License
Keywords: synthetic biology
Classifier: Development Status :: 3 - Alpha
Classifier: Intended Audience :: Developers
Classifier: License :: OSI Approved :: MIT License
Classifier: Programming Language :: Python :: 3 :: Only
Classifier: Programming Language :: Python :: 3.7
Classifier: Programming Language :: Python :: 3.8
Classifier: Programming Language :: Python :: 3.9
Classifier: Programming Language :: Python :: 3.10
Classifier: Programming Language :: Python :: 3.11
Requires-Python: >=3.7
License-File: LICENSE.txt
Requires-Dist: rdflib==6.*,>=6.1.1
Requires-Dist: python-dateutil==2.7.4
Requires-Dist: pyshacl~=0.21
